odd_airflow_integration/plugin.py
odd_airflow_integration/dir/airflow_odd_integrator.py
odd_airflow_integration/dir/listener.py
odd_airflow_2-0.0.5.dist-info/LICENSE
odd_airflow_2-0.0.5.dist-info/METADATA
odd_airflow_2-0.0.5.dist-info/WHEEL
odd_airflow_2-0.0.5.dist-info/entry_points.txt
odd_airflow_2-0.0.5.dist-info/top_level.txt
odd_airflow_2-0.0.5.dist-info/RECORD
